<?xml version="1.0" encoding="UTF-8"?>

<extension type="module" version="3.1.0" client="site" method="upgrade">
    <name>MDL Footer</name>
    <author>HariJR</author>
    <version>1.0.0</version>
    <description>Material Design Lite Style Footer</description>
    <files>
        <filename>mod_mdlfooter.xml</filename>
        <filename module="mod_mdlfooter">mod_mdlfooter.php</filename>
        <filename>index.html</filename>
        <filename>helper.php</filename>
        <filename>tmpl/default.php</filename>
        <filename>tmpl/index.html</filename>
    </files>
    <config>
    </config>
</extension>
